electrumsv_keepkey-7.0.3.post1.data/scripts/keepkeyctl
keepkeylib/__init__.py
keepkeylib/binance.py
keepkeylib/ckd_public.py
keepkeylib/client.py
keepkeylib/cosmos.py
keepkeylib/debuglink.py
keepkeylib/eos.py
keepkeylib/filecache.py
keepkeylib/mapping.py
keepkeylib/messages_binance_pb2.py
keepkeylib/messages_cosmos_pb2.py
keepkeylib/messages_eos_pb2.py
keepkeylib/messages_nano_pb2.py
keepkeylib/messages_osmosis_pb2.py
keepkeylib/messages_pb2.py
keepkeylib/messages_ripple_pb2.py
keepkeylib/messages_tendermint_pb2.py
keepkeylib/messages_thorchain_pb2.py
keepkeylib/nano.py
keepkeylib/protobuf_json.py
keepkeylib/ripple.py
keepkeylib/thorchain.py
keepkeylib/tools.py
keepkeylib/transport.py
keepkeylib/transport_fake.py
keepkeylib/transport_hid.py
keepkeylib/transport_pipe.py
keepkeylib/transport_serial.py
keepkeylib/transport_socket.py
keepkeylib/transport_udp.py
keepkeylib/transport_webusb.py
keepkeylib/tx_api.py
keepkeylib/types_pb2.py
keepkeylib/eth/__init__.py
keepkeylib/eth/ethereum_tokens.py
keepkeylib/eth/uniswap_tokens.py
keepkeylib/qt/__init__.py
keepkeylib/qt/pinmatrix.py
electrumsv_keepkey-7.0.3.post1.dist-info/COPYING
electrumsv_keepkey-7.0.3.post1.dist-info/METADATA
electrumsv_keepkey-7.0.3.post1.dist-info/WHEEL
electrumsv_keepkey-7.0.3.post1.dist-info/top_level.txt
electrumsv_keepkey-7.0.3.post1.dist-info/RECORD
