Metadata-Version: 2.1
Name: electrumsv-keepkey
Version: 7.0.3.post1
Summary: Python library for communicating with KeepKey Hardware Wallet
Home-page: https://github.com/electrumsv/python-keepkey
Author: TREZOR and KeepKey and ElectrumSV
Author-email: roger.taylor.email@gmail.com
Classifier: License :: OSI Approved :: GNU Lesser General Public License v3 (LGPLv3)
Classifier: Operating System :: POSIX :: Linux
Classifier: Operating System :: Microsoft :: Windows
Classifier: Operating System :: MacOS :: MacOS X
License-File: COPYING
Requires-Dist: ecdsa (>=0.9)
Requires-Dist: protobuf (>=3.0.0)
Requires-Dist: mnemonic (>=0.8)
Requires-Dist: hidapi (>=0.7.99.post15)
Requires-Dist: libusb1 (>=1.6)
